openexr_numpy/__init__.py
openexr_numpy/openexr_numpy.py
openexr_numpy/py.typed
openexr_numpy-0.0.8.dist-info/LICENSE
openexr_numpy-0.0.8.dist-info/METADATA
openexr_numpy-0.0.8.dist-info/WHEEL
openexr_numpy-0.0.8.dist-info/top_level.txt
openexr_numpy-0.0.8.dist-info/RECORD
