Metadata-Version: 2.1
Name: openexr_numpy
Version: 0.0.8
Summary: Module read and write Open EXR image files using numpy arrays.
Home-page: https://github.com/martinResearch/openexr_numpy
Author: Martin de La Gorce
Author-email: martin.delagorce@gmail.com
License: MIT
Requires-Python: >=3.8
License-File: LICENSE
Requires-Dist: numpy
Requires-Dist: openexr
Requires-Dist: imath
